vianaxabreu_de_toolkit/__init__.py
vianaxabreu_de_toolkit/main.py
vianaxabreu_de_toolkit/vm.py
vianaxabreu_de_toolkit-0.1.0.dist-info/METADATA
vianaxabreu_de_toolkit-0.1.0.dist-info/WHEEL
vianaxabreu_de_toolkit-0.1.0.dist-info/entry_points.txt
vianaxabreu_de_toolkit-0.1.0.dist-info/RECORD
